Metadata-Version: 2.1
Name: C-MTEB
Version: 1.1.1
Summary: Chinese Massive Text Embedding Benchmark
Home-page: https://github.com/FlagOpen/FlagEmbedding/tree/master/C_MTEB
Author-email: 2906698981@qq.com
